flask_paypal_lib/__init__.py
flask_paypal_lib/flaskpaypalsdk.py
flask_paypal_lib/sandbox.py
flaskpaypallib-0.0.2.dist-info/LICENSE
flaskpaypallib-0.0.2.dist-info/METADATA
flaskpaypallib-0.0.2.dist-info/WHEEL
flaskpaypallib-0.0.2.dist-info/top_level.txt
flaskpaypallib-0.0.2.dist-info/RECORD
